pter_analysis/__init__.py
pter_analysis/analysis.py
pter_analysis/config.py
pter_analysis/main.py
pter_analysis-1.0.1.dist-info/LICENSE
pter_analysis-1.0.1.dist-info/METADATA
pter_analysis-1.0.1.dist-info/WHEEL
pter_analysis-1.0.1.dist-info/entry_points.txt
pter_analysis-1.0.1.dist-info/top_level.txt
pter_analysis-1.0.1.dist-info/RECORD
