Metadata-Version: 2.1
Name: pter-analysis
Version: 1.0.1
Summary: Analysis of todotxt files using pter
Home-page: https://github.com/danielk333/pter_analysis
Author: Daniel Kastinen
Author-email: daniel.kastinen@irf.se
License: GNU-GPLv3
Platform: UNKNOWN
Classifier: Programming Language :: Python :: 3
Requires-Dist: pytodotxt (>=1.0.3)
Requires-Dist: pter (>=1.0.3)
Requires-Dist: matplotlib (>=3.2.1)
Requires-Dist: numpy (>=1.18.4)
Requires-Dist: click (>=7.0)
